my_sample_pack/__init__.py
my_sample_pack/meupack.py
myPackOnPython-0.0.1.dist-info/LICENSE
myPackOnPython-0.0.1.dist-info/METADATA
myPackOnPython-0.0.1.dist-info/WHEEL
myPackOnPython-0.0.1.dist-info/top_level.txt
myPackOnPython-0.0.1.dist-info/RECORD
