Metadata-Version: 2.1
Name: myPackOnPython
Version: 0.0.1
Summary: Pacote exemplo para o curso DIO
Home-page: https://github.com/pypa/sampleproject
Author: Paulo Soares Junior
Author-email: psjr01@icloud.com
License: UNKNOWN
Project-URL: Bug Tracker, https://github.com/pypa/sampleproject/issues
Platform: UNKNOWN
Classifier: Programming Language :: Python :: 3
Classifier: License :: OSI Approved :: MIT License
Classifier: Operating System :: OS Independent
Requires-Python: >=3.6
License-File: LICENSE
